wechrom/__init__.py
wechrom/prepare_memory.py
wechrom/single_nucleosome.py
wechrom/utils.py
wechrom/wechrom.py
wechrom/data/DNA.xml
wechrom/data/naked_database_list
wechrom/data/nucleo.xml
wechrom/data/nucleo_database_list
wechrom/data/nucleosome_database_list
wechrom/data/memory_template/1kx5.cif
wechrom/data/memory_template/B_AAGCGGGCACCTTGTCCGCGCAAGAAACTCTGAAGCTCATAAAAGCGGGACA.cif
wechrom/data/memory_template/B_ACCTCAAAGCACACGCCGGCTAGAAGGTACTACCTGGCATGCGATCGAGGTC.cif
wechrom/data/memory_template/B_ATCTTGAGTTCCACTGTCGCCCCATAGACCCGTTTACAGCTACTTTACAATA.cif
wechrom/data/memory_template/B_CGGACCACGTTAAAGTAGTAGAGTTCGTGGGCTTACGTATCCGACTTCATCA.cif
wechrom/data/memory_template/B_CTAGCTTCGAGTCGTAGCCCCGCAGCCGCATTAGGCGATCGGTAAGCTGACG.cif
wechrom/data/memory_template/B_GAAGCCTTCCGACGCGTTCCGTTCTAGTACGGTCCGGCATCTATGCTCCTCC.cif
wechrom/data/memory_template/B_GAATTAACGCCAAGTAGCGTACCCTTGCTACGTGATCACTGTTCACAGCCAG.cif
wechrom/data/memory_template/B_GGAATTTCCGGATGAGAGTCCGATGGCGCTCAACGGGCGACACGGGTTTAAT.cif
wechrom/data/memory_template/B_GTATGGCTCTGAACTCAATGGTGTTTACGAGTCTCAATTGATGCGTACGCCA.cif
wechrom/data/memory_template/B_GTTCTGATCGGGTAAGAGTTACTTAGGTGTGCACTCACTTGGACATAGGTGG.cif
wechrom-0.2.0.dist-info/LICENSE.md
wechrom-0.2.0.dist-info/METADATA
wechrom-0.2.0.dist-info/WHEEL
wechrom-0.2.0.dist-info/top_level.txt
wechrom-0.2.0.dist-info/RECORD
