Metadata-Version: 2.1
Name: wechrom
Version: 0.2.0
Summary: Python implementation for the WEChroM Model
Home-page: https://github.com/VickyLu001/wechrom
Download-URL: https://github.com/VickyLu001/wechrom/tarball/0.2.0
Author: Weiqi Lu
Author-email: luweicky@gmail.com
License: BSD
Platform: UNKNOWN
Classifier: Development Status :: 3 - Alpha
Classifier: Intended Audience :: Developers
Classifier: Programming Language :: Python :: 3
License-File: LICENSE.md
Requires-Dist: openmm
Requires-Dist: numpy
Requires-Dist: pandas
Requires-Dist: MDAnalysis
Requires-Dist: setuptools
Requires-Dist: tqdm
